{"name":"build-javascript","namedChunkGroups":{"app":{"name":"app","assets":[{"name":"webpack-runtime-6cb25fda91a5595e2f8a.js","size":3818},{"name":"framework-246111ab626f6a78c4f5.js","size":141427},{"name":"app-ed34aacb48bd5e556db6.js","size":120284}],"filteredAssets":0,"assetsSize":265529,"filteredAuxiliaryAssets":11,"auxiliaryAssetsSize":1069171},"component---src-pages-404-tsx":{"name":"component---src-pages-404-tsx","assets":[{"name":"component---src-pages-404-tsx-647ac3d6d70693ee24b8.js","size":771}],"filteredAssets":0,"assetsSize":771,"filteredAuxiliaryAssets":1,"auxiliaryAssetsSize":2122},"component---src-pages-index-tsx":{"name":"component---src-pages-index-tsx","assets":[{"name":"dfcf3a8d-61adf7a7f05e4fb2213e.js","size":7769},{"name":"component---src-pages-index-tsx-fcf81b7f4fd246ba7937.js","size":175120}],"filteredAssets":0,"assetsSize":182889,"filteredAuxiliaryAssets":4,"auxiliaryAssetsSize":604807}},"assetsByChunkName":{"app":["webpack-runtime-6cb25fda91a5595e2f8a.js","framework-246111ab626f6a78c4f5.js","app-ed34aacb48bd5e556db6.js"],"component---src-pages-404-tsx":["component---src-pages-404-tsx-647ac3d6d70693ee24b8.js"],"component---src-pages-index-tsx":["dfcf3a8d-61adf7a7f05e4fb2213e.js","component---src-pages-index-tsx-fcf81b7f4fd246ba7937.js"]},"childAssetsByChunkName":{}}